sym/awslambda/__init__.py
sym/awslambda/decorators.py
sym/awslambda/dispatch.py
sym/awslambda/errors.py
sym/awslambda/util.py
sym/awslambda/version.py
sym/awslambda/tests/__init__.py
sym/awslambda/tests/dispatch_test.py
sym/awslambda/tests/sym_action_test.py
sym_awslambda-1.0.4.dist-info/METADATA
sym_awslambda-1.0.4.dist-info/WHEEL
sym_awslambda-1.0.4.dist-info/top_level.txt
sym_awslambda-1.0.4.dist-info/RECORD
