Metadata-Version: 2.1
Name: sym-awslambda
Version: 1.0.4
Summary: Sym AWS Lambda Integration Helpers
Home-page: https://github.com/symopsio/sym-awslambda-py
Author: SymOps, Inc.
Author-email: pypi@symops.io
License: UNKNOWN
Platform: UNKNOWN
Classifier: Programming Language :: Python :: 3
Classifier: License :: OSI Approved :: Apache Software License
Requires-Python: >=3.8
Requires-Dist: boto3 (>=1.14)
Requires-Dist: protobuf
Requires-Dist: sym-types
